ligo_segments-1.4.0-py3.7-nspkg.pth
ligo/segments/__init__.py
ligo/segments/__segments.cp37-win_amd64.pyd
ligo/segments/utils.py
ligo_segments-1.4.0.dist-info/LICENSE
ligo_segments-1.4.0.dist-info/METADATA
ligo_segments-1.4.0.dist-info/WHEEL
ligo_segments-1.4.0.dist-info/namespace_packages.txt
ligo_segments-1.4.0.dist-info/top_level.txt
ligo_segments-1.4.0.dist-info/RECORD
